clang_format/__init__.py
clang_format/clang_format_diff.py
clang_format/git_clang_format.py
clang_format/data/bin/clang-format
clang_format.libs/libgcc_s-0cd532bd.so.1
clang_format.libs/libstdc++-5d72f927.so.6.0.33
clang_format-21.1.5.dist-info/METADATA
clang_format-21.1.5.dist-info/WHEEL
clang_format-21.1.5.dist-info/entry_points.txt
clang_format-21.1.5.dist-info/RECORD
clang_format-21.1.5.dist-info/licenses/COPYING.md
clang_format-21.1.5.dist-info/licenses/LICENSE.md
