Metadata-Version: 2.2
Name: clang-format
Version: 21.1.5
Summary: Clang-Format is an LLVM-based code formatting tool
Author-Email: Dominic Kempf <ssc@iwr.uni-heidelberg.de>
License: Apache 2.0
Classifier: Programming Language :: C
Classifier: Programming Language :: C++
Classifier: Operating System :: OS Independent
Classifier: License :: OSI Approved :: Apache Software License
Classifier: Intended Audience :: Developers
Classifier: Topic :: Software Development :: Quality Assurance
Project-URL: Clang, http://clang.llvm.org/
Project-URL: Documentation, https://clang.llvm.org/docs/ClangFormat.html
Project-URL: Download, https://github.com/llvm/llvm-project/releases
Project-URL: Source, https://github.com/ssciwr/clang-format-wheel
